LICENSE
MANIFEST.in
README.md
requirements.txt
setup.cfg
setup.py
src/pyvesync/__init__.py
src/pyvesync/helpers.py
src/pyvesync/vesync.py
src/pyvesync/vesyncbasedevice.py
src/pyvesync/vesyncbulb.py
src/pyvesync/vesyncfan.py
src/pyvesync/vesyncoutlet.py
src/pyvesync/vesyncswitch.py
src/pyvesync_api.egg-info/PKG-INFO
src/pyvesync_api.egg-info/SOURCES.txt
src/pyvesync_api.egg-info/dependency_links.txt
src/pyvesync_api.egg-info/not-zip-safe
src/pyvesync_api.egg-info/requires.txt
src/pyvesync_api.egg-info/top_level.txt
src/tests/__init__.py
src/tests/call_json.py
src/tests/test_air_pur.py
src/tests/test_vesync.py
src/tests/test_vesync_10a.py
src/tests/test_vesync_15a.py
src/tests/test_vesync_7aswitch.py
src/tests/test_vesync_bulbs.py
src/tests/test_vesync_devices.py
src/tests/test_vesync_login.py
src/tests/test_vesync_outdoor.py
src/tests/test_wall_switch.py