Metadata-Version: 2.1
Name: pyvesync-api
Version: 1.2.0
Summary: pyvesync is a library to manage Etekcity                 Devices and Levoit Air Purifier
Home-page: https://github.com/djtimca/pyvesync
Author: Tim Empringham
Author-email: tim.empringham@live.ca
License: MIT
Keywords: iot,vesync
Platform: UNKNOWN
Classifier: License :: OSI Approved :: MIT License
Classifier: Intended Audience :: Developers
Classifier: Intended Audience :: End Users/Desktop
Classifier: Natural Language :: English
Classifier: Programming Language :: Python :: 3.5
Requires-Python: >=3.5
